shapleychains/__init__.py
shapleychains/chaincontrib.py
shapleychains/functions.py
shapleychains-0.0.1.dist-info/LICENSE
shapleychains-0.0.1.dist-info/METADATA
shapleychains-0.0.1.dist-info/WHEEL
shapleychains-0.0.1.dist-info/top_level.txt
shapleychains-0.0.1.dist-info/RECORD
