Metadata-Version: 2.1
Name: shapleychains
Version: 0.0.1
Home-page: https://github.com/cwayad/shapleychains.git
Author: Célia Wafa AYAD
Author-email: celiane.ayad@gmail.com
License-File: LICENSE
Requires-Dist: pandas
Requires-Dist: numpy
Requires-Dist: sklearn
Requires-Dist: shap
Requires-Dist: matplotlib
